Workbook

Sheet 进度总览
A2: AI 解决方案工程师学习进度
A3: 70 天，10 周。2026-10-06 开始，每晚 22:30（北京时间）跟进。
A4: 每日约 3–4 小时；每周第 7 天复盘缓冲约 2.5 小时
A5: 计划天数 | B5: =COUNTA(每日清单!$A$6:$A$75) -> 70 | C5: 已完成 | D5: =COUNTIFS(每日清单!$H$6:$H$75,"已完成") -> 0 | E5: 进行中 | F5: =COUNTIFS(每日清单!$H$6:$H$75,"进行中") -> 0 | G5: 完成率 | H5: =D5/B5 -> 0
A6: 计划小时 | B6: =SUM(每日清单!$L$6:$L$75) -> 236.25 | C6: 实际小时 | D6: =SUM(每日清单!$Q$6:$Q$75) -> 0 | E6: 未开始 | F6: =COUNTIFS(每日清单!$H$6:$H$75,"未开始") -> 70 | G6: 计划结束日期 | H6: =MAX(每日清单!$K$6:$K$75) -> 46370
A8: 统计范围 | B8: 完成率只统计本次 70 日计划，不代表已有技能归零。
A9: 验收口径 | B9: 自报完成后，须提供运行结果并独立解释关键代码；验收通过才标记“已完成”。
A11: 周次 | B11: 本周重点 | C11: 计划天数 | D11: 已完成 | E11: 进行中 | F11: 完成率 | G11: 周验收目标 | H11: 原计划
A12: 1 | B12: 补齐已有项目的可验收交付 | C12: =COUNTIFS(每日清单!$B$6:$B$75,$A12) -> 7 | D12: =COUNTIFS(每日清单!$B$6:$B$75,$A12,每日清单!$H$6:$H$75,"已完成") -> 0 | E12: =COUNTIFS(每日清单!$B$6:$B$75,$A12,每日清单!$H$6:$H$75,"进行中") -> 0 | F12: =D12/C12 -> 0 | G12: 已有 API 通过真实 HTTP 正常/错误路径；原数据保留；清洗可重复；LLM 调用有错误处理。 | H12: Day01–14
A13: 2 | B13: 做出带来源的最小 RAG | C13: =COUNTIFS(每日清单!$B$6:$B$75,$A13) -> 7 | D13: =COUNTIFS(每日清单!$B$6:$B$75,$A13,每日清单!$H$6:$H$75,"已完成") -> 0 | E13: =COUNTIFS(每日清单!$B$6:$B$75,$A13,每日清单!$H$6:$H$75,"进行中") -> 0 | F13: =D13/C13 -> 0 | G13: 10 道固定题中 8 道可回答题至少 6 道命中来源；2 道无答案题均明确拒答；重启后索引可用。 | H13: Day15–21
A14: 3 | B14: 完成业务知识库 MVP | C14: =COUNTIFS(每日清单!$B$6:$B$75,$A14) -> 7 | D14: =COUNTIFS(每日清单!$B$6:$B$75,$A14,每日清单!$H$6:$H$75,"已完成") -> 0 | E14: =COUNTIFS(每日清单!$B$6:$B$75,$A14,每日清单!$H$6:$H$75,"进行中") -> 0 | F14: =D14/C14 -> 0 | G14: 一类业务、20–30 份小文档、可操作页面与引用；形成 30 题固定评测集并封存 10 题。 | H14: Day22–28
A15: 4 | B15: 评测、修复并验收项目一 | C15: =COUNTIFS(每日清单!$B$6:$B$75,$A15) -> 7 | D15: =COUNTIFS(每日清单!$B$6:$B$75,$A15,每日清单!$H$6:$H$75,"已完成") -> 0 | E15: =COUNTIFS(每日清单!$B$6:$B$75,$A15,每日清单!$H$6:$H$75,"进行中") -> 0 | F15: =D15/C15 -> 0 | G15: 按P19逐题口径：20道有答案题Hit@5至少16/20，引用正确至少17/20；10道无答案题拒答至少8/10；独立10题首次成绩与配置单列。 | H15: Day29–35
A16: 5 | B16: 构建安全的只读工具链 | C16: =COUNTIFS(每日清单!$B$6:$B$75,$A16) -> 7 | D16: =COUNTIFS(每日清单!$B$6:$B$75,$A16,每日清单!$H$6:$H$75,"已完成") -> 0 | E16: =COUNTIFS(每日清单!$B$6:$B$75,$A16,每日清单!$H$6:$H$75,"进行中") -> 0 | F16: =D16/C16 -> 0 | G16: 工具选择和参数可追溯；只读查询、行数/耗时限制生效；至少 6 个危险调用被阻止。 | H16: Day36–42
A17: 6 | B17: 完成 Business Analyst 项目二 | C17: =COUNTIFS(每日清单!$B$6:$B$75,$A17) -> 7 | D17: =COUNTIFS(每日清单!$B$6:$B$75,$A17,每日清单!$H$6:$H$75,"已完成") -> 0 | E17: =COUNTIFS(每日清单!$B$6:$B$75,$A17,每日清单!$H$6:$H$75,"进行中") -> 0 | F17: =D17/C17 -> 0 | G17: 12题开发/回归至少10题通过，4题独立至少3题通过且缺数据不编造；危险请求全部受限；能独立演示并核对数据。 | H17: Day43–49
A18: 7 | B18: 将两个 Demo 做成可复现交付 | C18: =COUNTIFS(每日清单!$B$6:$B$75,$A18) -> 7 | D18: =COUNTIFS(每日清单!$B$6:$B$75,$A18,每日清单!$H$6:$H$75,"已完成") -> 0 | E18: =COUNTIFS(每日清单!$B$6:$B$75,$A18,每日清单!$H$6:$H$75,"进行中") -> 0 | F18: =D18/C18 -> 0 | G18: 两项目在独立环境按 README 启动并通过真实 HTTP 检查；离线 CI 通过；具备部署、日志与恢复记录。 | H18: Day50–56
A19: 8 | B19: 形成第三项目：企业实施方案 | C19: =COUNTIFS(每日清单!$B$6:$B$75,$A19) -> 7 | D19: =COUNTIFS(每日清单!$B$6:$B$75,$A19,每日清单!$H$6:$H$75,"已完成") -> 0 | E19: =COUNTIFS(每日清单!$B$6:$B$75,$A19,每日清单!$H$6:$H$75,"进行中") -> 0 | F19: =D19/C19 -> 0 | G19: 完成 10–15 页方案：需求、架构、选型、数据、安全、实施、验收、风险和带假设的成本/ROI。 | H19: Day57–70
A20: 9 | B20: 准备作品集、简历与面试证据 | C20: =COUNTIFS(每日清单!$B$6:$B$75,$A20) -> 7 | D20: =COUNTIFS(每日清单!$B$6:$B$75,$A20,每日清单!$H$6:$H$75,"已完成") -> 0 | E20: =COUNTIFS(每日清单!$B$6:$B$75,$A20,每日清单!$H$6:$H$75,"进行中") -> 0 | F20: =D20/C20 -> 0 | G20: 两 Demo 和方案有统一作品集入口；两版简历、8 条岗位样本、2 次模拟面试及修订记录。 | H20: Day71–77
A21: 10 | B21: 开展投递反馈并完成最终验收 | C21: =COUNTIFS(每日清单!$B$6:$B$75,$A21) -> 7 | D21: =COUNTIFS(每日清单!$B$6:$B$75,$A21,每日清单!$H$6:$H$75,"已完成") -> 0 | E21: =COUNTIFS(每日清单!$B$6:$B$75,$A21,每日清单!$H$6:$H$75,"进行中") -> 0 | F21: =D21/C21 -> 0 | G21: 本人完成至少 6 次匹配投递或记录客观阻碍；两 Demo 可复现，方案可讲解，形成下一轮调整清单。 | H21: Day78–84
A24: 最终交付
A25: 交付 1 | B25: 企业知识库问答：可复现运行，回答可追溯引用，无资料时拒答，并附固定评测报告。
A26: 交付 2 | B26: 业务数据分析助手：只读查询，结果可核对，图表与解释一致，出错时给出明确反馈。
A27: 交付 3 | B27: 企业 AI 解决方案：10–15 页，覆盖需求、架构、选型、实施、成本 ROI、风险、验收和运维。
A29: 填写方法 | B29: 每天填写状态、实际小时、证据与卡点；证据可用代码位置、运行输出或演示链接。
B30: “未开始 / 进行中 / 已完成”为唯一状态。未过验收就继续补缺，并顺延后续学习。
B31: 黄色单元格可编辑。资料链接可点击，首列和表头已冻结，可按周次或状态筛选。
B32: 每日跟进结合仓库变化和你的反馈调整任务，静态 Excel 不会自行改写学习安排。

Sheet 每日清单
A2: 每日学习清单
A3: 每晚 22:30（北京时间）跟进。淡黄色格可填写；验收通过后再选“已完成”。
A5: Day | B5: 周次 | C5: 阶段 | D5: 学习主题 | E5: 今日任务 | F5: 今日产出 | G5: 验收标准 | H5: 完成状态 | I5: 完成日期 | J5: 备注 | K5: 计划日期 | L5: 计划小时 | M5: 资料 1 | N5: 资料 2 | O5: 证据 | P5: 原计划映射 | Q5: 实际小时
A6: P01 | B6: 1 | C6: 阶段一：补缺与 RAG 项目 | D6: 验收现有 FastAPI | E6: 目标：确认现有接口真实可用，并留下可重复执行的证据。 1）按 week02/day11 的现有说明启动服务，记录环境和命令。 2）实测健康检查、查询、创建、错误请求，并记下当前缺口。 3）独立给商品增加可选 category 字段，不照抄完整答案，保持原请求兼容。 | F6: reports/P01-api-baseline.md、HTTP 请求样例与独立 category 字段改动 | G6: 1）GET /health 返回 200；/docs 能打开。 2）至少 6 次 HTTP 请求覆盖读取、创建、无效参数和不存在资源，并记录响应。 3）分别创建带/不带 category 的商品，两者均成功；查询能看到对应分类或默认空值。 4）区分已经通过、未通过、尚未验证，写出不超过 3 个优先缺口。 | H6: 未开始 | K6: 46301 | L6: 3.5 | M6: FastAPI：第一步与接口文档 | N6: FastAPI：请求体 | P6: 原 Day13–14：只补运行验收，不重做基础。
A7: P02 | B7: 1 | C7: 阶段一：补缺与 RAG 项目 | D7: 数据清洗可复现 | E7: 目标：将现有电影数据处理变成不覆盖原始文件的可复现流程。 1）复用已有 Pandas 处理逻辑，把输入、输出路径和清洗规则写明确。 2）对缺失值、重复值和类型转换记录前后数量，再连续运行两次。 | F7: 可执行清洗脚本、独立输出数据与 reports/P02-cleaning.md | G7: 1）原 CSV 的内容哈希在运行前后相同，清洗结果写入新路径。 2）两次运行输出行数与核心汇总一致，记录清洗前后行数及各类异常数。 3）从项目根目录按说明可运行，不依赖个人绝对路径。 | H7: 未开始 | K7: 46302 | L7: 3.5 | M7: pandas：缺失数据 | N7: pandas：文件读写 | P7: 原 Day11：补可复现与原数据保护；基础操作已具备。
A8: P03 | B8: 1 | C8: 阶段一：补缺与 RAG 项目 | D8: 数据分析 API | E8: 目标：让已有分析逻辑通过受校验的接口返回业务结果。 1）为清洗结果增加一个 /analyze 接口，输入筛选条件，输出样本量和 2 个指标。 2）准备小样本手算基准，实测有效、无结果与非法输入。 | F8: 数据分析接口、3 组 HTTP 验收记录 | G8: 1）1 组正常请求的样本量和 2 个指标与手算基准一致。 2）空结果返回约定的业务响应；非法参数返回 4xx 而非 500。 3）/docs 能说明输入字段、单位和输出指标口径。 | H8: 未开始 | K8: 46303 | L8: 3.5 | M8: FastAPI：请求体 | N8: FastAPI：处理错误 | P8: 原 Day12–13：合并业务口径与 API 交付。
A9: P04 | B9: 1 | C9: 阶段一：补缺与 RAG 项目 | D9: LLM 调用的失败处理 | E9: 目标：将现有 DeepSeek 流式代码补到可诊断、可结束的状态。 1）沿用现有模型和配置，封装流式读取，处理空增量与正常结束。 2）配置超时和有限重试，用可控模拟覆盖限流、超时及认证失败。 | F9: 可复用 LLM 调用模块与 reports/P04-llm-errors.md | G9: 1）至少 1 次真实调用完整结束，输出非空；不在记录中放密钥。 2）超时/限流最多重试 2 次；认证失败直接报错，不无限等待。 3）3 类故障记录含错误类别和处理结果；无真实凭据时明确标记待真实验证。 | H9: 未开始 | K9: 46304 | L9: 3.5 | M9: DeepSeek：流式输出 | N9: DeepSeek：错误码 | P9: 原 Day05–07 的工程补缺；保留现有 DeepSeek 路线。
A10: P05 | B10: 1 | C10: 阶段一：补缺与 RAG 项目 | D10: 结构化业务输出 | E10: 目标：让模型结果能被程序校验，并对异常输出给出可理解的提示。 1）定义包含结论、依据和限制的简单 JSON 输出结构。 2）在现有调用上加结构校验，并准备错误 JSON、缺字段和空输出样例。 | F10: 结构化输出示例与 5 条校验记录 | G10: 1）2 个正常例子能通过结构校验，并显示结论与依据。 2）3 个异常例子均被识别，不把原始异常堆栈直接展示给使用者。 3）缺少数据依据时输出限制说明，不编造数字。 | H10: 未开始 | K10: 46305 | L10: 3.5 | M10: DeepSeek：JSON Output | N10: FastAPI：请求体 | P10: 原基础阶段补缺：为 RAG 和 Agent 准备可校验输出。
A11: P06 | B11: 1 | C11: 阶段一：补缺与 RAG 项目 | D11: 目标岗位与项目问题 | E11: 目标：用真实岗位需求确定两项目的业务边界。 1）收集 6–8 条可申请的 AI 实施/解决方案/应用工程岗位，保存链接和日期。 2）归纳高频能力，选定知识库业务场景与分析业务场景，各写一页范围说明。 | F11: reports/job-sample-v1.md 与两个项目的一页需求 | G11: 1）至少 6 条岗位记录含职责、硬性条件、地点/工作形式与原链接。 2）两项目各写清使用者、问题、输入输出和 3 条验收要求。 3）将高频要求标成已有证据/待补缺；不把高级岗位年限要求当作本轮必达。 | H11: 未开始 | K11: 46306 | L11: 3.5 | M11: Microsoft Learn：解决方案架构师职业路径 | N11: Microsoft Learn：RAG 概述 | P11: 原 Day01 目标确认补充；提前引入原 Day71 的岗位匹配。
A12: P07 | B12: 1 | C12: 阶段一：补缺与 RAG 项目 | D12: 第一周复盘与缓冲 | E12: 目标：确认基础缺口已补齐，再进入 RAG。 1）重跑本周关键 HTTP、清洗和 LLM 验收，整理证据链接。 2）只修复最高优先级缺口；为下一周保留或调整任务量。 | F12: reports/W01-review.md 与下一周调整记录 | G12: 1）逐项给出周关口通过/未通过/未验证，均有证据。 2）能用 5 分钟解释数据来源、接口口径和 1 个失败处理。 3）未达关口时插入S编号补练，顺延下一P及后续日期，保留原任务并记录原因，不叠加任务。 | H12: 未开始 | K12: 46307 | L12: 2.5 | M12: FastAPI：测试 | N12: GitHub Docs：关于 README | P12: 原 Day14 复盘；本日不新增理论。
A13: P08 | B13: 2 | C13: 阶段一：补缺与 RAG 项目 | D13: 中文文本向量 | E13: 目标：用少量业务文本验证相似度能表达语义关联。 1）选择一个明确支持中文的轻量 Embedding 模型，在 CPU 上编码 10 条业务句子。 使用独立、受相关依赖支持的Python环境，先核对兼容版本；保留已有.venv。 2）比较 3 个近义查询和 2 个无关查询的排序，记录模型版本。 | F13: Embedding 小实验与 reports/P08-similarity.md | G13: 1）10 条文本均生成相同维数的向量，无空值。 2）至少 3 个近义查询的相关文本进入前 3，失败样例被保留。 3）记录模型名、维数、首次加载耗时与运行命令。 | H13: 未开始 | J13: 预计时长包含排错。安装/下载排错累计超过60分钟，就插入环境补课并顺延；保留现有环境，禁止把任务叠到同一天。 | K13: 46308 | L13: 3.5 | M13: Sentence Transformers：语义相似度 | P13: 原 Day15：Embedding；不训练模型。
A14: P09 | B14: 2 | C14: 阶段一：补缺与 RAG 项目 | D14: 带来源的文档分块 | E14: 目标：将业务文档切成能追溯出处的检索单位。 1）选 5 份公开或脱敏的短文档，保留标题、版本和来源。 2）实现一种按标题/长度的分块方式，记录块 ID、文档 ID 和位置。 | F14: 5 份样本文档、分块脚本与 chunks.jsonl | G14: 1）每块都有唯一 ID、原文和来源定位字段。 2）人工抽查 10 个块能回到原文，关键段落没有被遗漏。 3）记录分块长度和重叠参数，以及 2 个跨段问题。 | H14: 未开始 | K14: 46309 | L14: 3.5 | M14: Microsoft Learn：RAG 文档分块 | P14: 原 Day16：文本处理与分块。
A15: P10 | B15: 2 | C15: 阶段一：补缺与 RAG 项目 | D15: 持久化向量索引 | E15: 目标：将文档向量存入可重启使用的本地索引。 1）用 Chroma 保存分块文本、向量和来源元数据。 2）实现按稳定 ID 写入和更新，重启后重新查询。 | F15: 索引构建命令、持久化目录与索引统计 | G15: 1）索引条目数与有效块数一致。 2）同一批文档重复导入不增加重复条目。 3）重启进程后能查询同一索引，并取回来源字段。 | H15: 未开始 | J15: 预计时长包含排错。安装/下载排错累计超过60分钟，就插入环境补课并顺延；保留现有环境，禁止把任务叠到同一天。 | K15: 46310 | L15: 3.5 | M15: Chroma：快速开始 | P15: 原 Day17：向量库与索引。
A16: P11 | B16: 2 | C16: 阶段一：补缺与 RAG 项目 | D16: 检索及命中检查 | E16: 目标：让业务问题返回可检查的 top-k 证据。 1）实现检索接口或命令，返回 top-5 文本、分数与来源。 2）写 8 道可回答题和 2 道无答案题，并手工标注预期文档。 | F16: 检索程序与 10 题最小检索集 | G16: 1）8 道可回答题至少 6 道在 top-5 中命中预期文档。 2）每个结果都显示块 ID、来源和分数，不只打印答案。 3）保留全部失败题及初步原因，不删除难题美化结果。 | H16: 未开始 | K16: 46311 | L16: 3.5 | M16: Sentence Transformers：语义检索 | N16: Chroma：快速开始 | P16: 原 Day18：相似度检索与检索评估起步。
A17: P12 | B17: 2 | C17: 阶段一：补缺与 RAG 项目 | D17: 最小 RAG 回答 | E17: 目标：让模型仅凭检索证据回答，并给出来源。 1）把检索结果编号后作为上下文，接入现有 DeepSeek 调用。 2）要求回答附来源编号；上下文不足时说明无法确认。 | F17: 可运行的问答命令与 5 条带引用示例 | G17: 1）5 道样例题都展示回答及可展开/查看的原文片段。 2）引用编号只能来自本次检索结果，不接受不存在的来源。 3）至少 1 道无答案题明确说明知识库缺少依据。 | H17: 未开始 | K17: 46312 | L17: 3.5 | M17: Microsoft Learn：RAG 概述 | N17: DeepSeek：首次调用 | P17: 原 Day19：检索增强生成最小闭环。
A18: P13 | B18: 2 | C18: 阶段一：补缺与 RAG 项目 | D18: RAG API 与来源结构 | E18: 目标：把最小 RAG 封装成可供页面调用的接口。 1）增加 /ask 接口，返回 answer、sources 和基本耗时。 2）校验空问题、超长问题以及索引不存在的响应。 | F18: RAG API 与 4 组真实 HTTP 记录 | G18: 1）正常请求返回回答、至少 1 条可核对来源及耗时。 2）空问题、超长问题和缺失索引均返回约定错误。 3）/docs 中输入和输出结构完整，源码不包含密钥。 | H18: 未开始 | K18: 46313 | L18: 3.5 | M18: FastAPI：请求体 | N18: FastAPI：处理错误 | P18: 原 Day20：RAG 服务封装。
A19: P14 | B19: 2 | C19: 阶段一：补缺与 RAG 项目 | D19: 第二周最小闭环验收 | E19: 目标：确认检索、回答与引用形成可靠的最小路径。 1）运行固定 10 题，记录检索、回答和引用结果。 2）只修复最影响演示的一项问题，并写下一周范围。 | F19: reports/W02-review.md 与最小 RAG 演示记录 | G19: 1）8 道可回答题至少 6 道命中来源，2 道无答案题均明确拒答。 2）重启服务后无需重建索引即可完成一次问答。 3）能用5分钟解释Embedding、分块、检索、生成各自职责；未通过则插入S编号补练，顺延P15及后续，保留原任务。 | H19: 未开始 | K19: 46314 | L19: 2.5 | M19: Microsoft Learn：RAG 概述 | N19: GitHub Docs：关于 README | P19: 原 Day21：周复盘与缓冲，不新增理论。
A20: P15 | B20: 3 | C20: 阶段一：补缺与 RAG 项目 | D20: 知识库业务验收范围 | E20: 目标：把通用问答收敛为一个可以交付的业务 MVP。 1）沿用 P06 场景，明确一个用户角色、三类高频问题和业务边界。 2）列出功能必须有/可以延后项，以及无答案时的用户提示。 | F20: project-rag/docs/requirements.md | G20: 1）形成 3 个用户故事，每个都有输入、预期结果和失败处理。 2）MVP 必须功能不超过 5 项，并写清文档更新者和使用者。 3）明确不支持的任务与敏感数据边界，不临时扩大范围。 | H20: 未开始 | K20: 46315 | L20: 3.5 | M20: Microsoft Learn：RAG 概述 | N20: Microsoft Learn：Well-Architected 框架 | P20: 原 Day22：知识库需求与业务范围。
A21: P16 | B21: 3 | C21: 阶段一：补缺与 RAG 项目 | D21: 知识库导入与更新 | E21: 目标：将业务资料稳定导入，并支持单文档更新。 1）整理 20–30 份小型公开/脱敏文本或 Markdown 文档；本轮不加入扫描 OCR。 2）在已有导入流程中增加文档版本或内容哈希，验证更新和删除失效内容。 | F21: 知识库目录、来源清单和更新命令 | G21: 1）每份资料有来源、采集日期和使用范围记录。 2）同一文档重复导入不重复，修改 1 份文档后只更新对应块。 3）删除/失效的 1 份测试文档不再出现在检索结果中。 | H21: 未开始 | K21: 46316 | L21: 3.5 | M21: Chroma：快速开始 | N21: Microsoft Learn：RAG 文档分块 | P21: 原 Day23：文档接入与更新；限制输入格式控制工作量。
A22: P17 | B22: 3 | C22: 阶段一：补缺与 RAG 项目 | D22: 可操作的问答页面 | E22: 目标：让使用者无需命令行就能完成问答。 1）用 Streamlit 为已有 RAG API 制作输入、回答和来源区域。 2）展示加载状态、清空会话按钮与失败提示。 | F22: 知识库问答页面与启动说明 | G22: 1）从页面提交 3 个问题均能显示回答和来源。 2）请求期间有等待提示，失败时有可理解的说明。 3）清空按钮会移除当前会话内容；界面不显示密钥或堆栈。 | H22: 未开始 | K22: 46317 | L22: 3.5 | M22: Streamlit：聊天应用教程 | N22: Streamlit：Session State | P22: 原 Day24：知识库交互页面。
A23: P18 | B23: 3 | C23: 阶段一：补缺与 RAG 项目 | D23: 引用核对与证据展示 | E23: 目标：让用户能够快速核对答案中的事实。 1）在页面展示来源标题、文档位置和命中原文。 2）对回答中的核心事实检查来源支持；修复虚构或错配引用。 | F23: 来源展示组件与 10 条人工核对记录 | G23: 1）抽查 10 个有答案回答，至少 8 个回答的全部核心事实均有对应引用原文支持；按回答计数。 2）所有显示的引用 ID 都存在且能打开/展开对应片段。 3）对无依据结论明确标注无法确认，不用相似片段冒充证据。 | H23: 未开始 | K23: 46318 | L23: 3.5 | M23: Microsoft Learn：RAG 概述 | N23: Streamlit：聊天应用教程 | P23: 原 Day25：可追溯回答与引用核验。
A24: P19 | B24: 3 | C24: 阶段一：补缺与 RAG 项目 | D24: 固定业务评测集 | E24: 目标：建立不会随调参被改写的业务验收依据。 1）编写 30 道业务题：20 道有答案、10 道无答案，标注来源与判定要点。 2）划分开发集 20 题和独立集 10 题，独立集本周封存。 | F24: eval/questions.jsonl、评分规则与冻结版本号 | G24: 1）每题有 ID、问题、题型、预期要点、来源或无答案原因。 2）开发集含 14 道有答案和 6 道无答案；独立集含 6 道有答案和 4 道无答案。 3）题集和评分口径有版本；后续修题记录原因，禁止静默删难题。 4）固定口径：Hit@5=top-5命中至少一个预标注充分证据片段的题数/有答案题数；引用正确率=全部核心事实均有正确引用支持的回答数/有答案题数；拒答率=明确拒答且无编造的题数/无答案题数。 | H24: 未开始 | K24: 46319 | L24: 3.5 | M24: Microsoft Learn：RAG 概述 | N24: pytest：入门 | P24: 原 Day26：业务题集与评测口径。
A25: P20 | B25: 3 | C25: 阶段一：补缺与 RAG 项目 | D25: 业务 MVP 全流程演示 | E25: 目标：验证使用者从启动到核对证据能完成任务。 1）按一名新使用者的路径执行启动、提问、查看引用与文档更新。 2）修复阻断问题并录制一个 3–5 分钟演示。 | F25: MVP 演示视频/截图流程与阻断问题清单 | G25: 1）连续完成 3 个业务问题和 1 个无答案问题。 2）更新一份文档后页面可检索到新内容，无需修改代码。 3）记录全部阻断缺陷，至少修复最严重的 1 项或说明客观阻碍。 | H25: 未开始 | K25: 46320 | L25: 3.5 | M25: GitHub Docs：关于 README | N25: Streamlit：聊天应用教程 | P25: 原 Day27：知识库 MVP 集成与展示。
A26: P21 | B26: 3 | C26: 阶段一：补缺与 RAG 项目 | D26: 第三周复盘与冻结范围 | E26: 目标：确认 MVP 可用，进入评测和修复阶段。 1）按需求逐项核对页面、引用和更新功能，检查评测集完整性。 2）冻结本轮功能范围，只排缺陷与评测工作。 | F26: reports/W03-review.md 与 MVP 验收表 | G26: 1）至少 3 个用户故事均有一次实际操作证据。 2）30 题清单齐全且独立 10 题未用于调参。 3）必须功能未通过则插入S编号补练，顺延P22及后续，保留原任务；不把新功能挤入评测周。 | H26: 未开始 | K26: 46321 | L26: 2.5 | M26: GitHub Docs：关于 README | N26: Microsoft Learn：RAG 概述 | P26: 原 Day28：周复盘与缓冲，不新增理论。
A27: P22 | B27: 4 | C27: 阶段一：补缺与 RAG 项目 | D27: 检索基线量化 | E27: 目标：分开测量检索命中与回答问题。 1）在14道开发集有答案题上运行检索，按P19固定口径计算逐题Hit@5，并显示命中数/总题数。 2）记录每题 top-5、命中与否、耗时，并归类失败原因。 | F27: eval/retrieval-baseline.json 与失败分类表 | G27: 1）14 道开发集有答案题全部有逐题命中结果及总 Hit@5。 2）每道失败题归到资料缺失、分块、检索或标注问题之一。 3）保存模型版本、分块参数、top-k 和索引版本，可重跑。 | H27: 未开始 | K27: 46322 | L27: 3.5 | M27: Sentence Transformers：语义检索 | N27: pytest：入门 | P27: 原 Day29：检索评估基线。
... A29: P24 | B29: 4 | C29: 阶段一：补缺与 RAG 项目 | D29: 回答依据与拒答 | E29: 目标：减少已有证据被误读及缺证据时的编造。 1）为开发集回答做人工核对，分别标记事实错误、引用错配和拒答失败。 2）只调整回答提示或上下文组织，重跑受影响题。 | F29: 回答质量评分表与提示版本 | G29: 1）14 道有答案题都核对核心事实与引用是否支持。 2）6 道无答案题记录是否明确拒答及是否夹带编造。 3）按P19逐题口径报告修改前后引用正确率与拒答率，保留失败例；若全部通过则保存2个边界用例。 | H29: 未开始 | K29: 46324 | L29: 3.5 | M29: Microsoft Learn：RAG 概述 | N29: DeepSeek：JSON Output | P29: 原 Day31：生成质量、引用与无答案策略。
A30: P25 | B30: 4 | C30: 阶段一：补缺与 RAG 项目 | D30: 知识库提示注入检查 | E30: 目标：检验不可信资料不能改变应用行为。 1）制作 5 个对抗问题/文档片段，包括伪系统指令、索取密钥和诱导无引用回答。 2）明确文档仅是数据，加上必要的输入和输出限制后复测。 | F30: 5 条对抗用例与风险记录 | G30: 1）5 个用例均记录预期、实际响应与是否通过。 2）不输出密钥、环境变量或未提供的私人内容。 3）不能承诺彻底防注入；残余风险与应用权限边界写入说明。 | H30: 未开始 | K30: 46325 | L30: 3.5 | M30: OWASP GenAI：提示注入 | P30: 原 Day32：RAG 安全边界与对抗检查。
A31: P26 | B31: 4 | C31: 阶段一：补缺与 RAG 项目 | D31: 独立评测与成本记录 | E31: 目标：用未调参的题目检验泛化，并测量真实成本和延迟。 1）冻结配置后首次运行独立 10 题，人工按同一规则评分。 2）分别汇总开发20题、首次独立10题和全量30题结果，记录用量与延迟；全量结果不可称泛化准确率。 | F31: 独立评测报告、全量指标和成本估算 | G31: 1）独立10题结果与冻结配置单列；若后续参考这些结果调参，该集改标回归集，原独立成绩不得改写。 2）按P19口径：全量20道有答案题Hit@5至少16/20、逐题引用正确至少17/20；10道无答案题正确拒答至少8/10，未达标如实记录。 3）报告运行环境、样本数、延迟中位数/P95 与价格日期；用量缺失时标为估算。 | H31: 未开始 | K31: 46326 | L31: 3.75 | M31: DeepSeek：模型与价格 | N31: Microsoft Learn：RAG 概述 | P31: 原 Day33：独立验收、时延与成本。
A32: P27 | B32: 4 | C32: 阶段一：补缺与 RAG 项目 | D32: RAG 交付说明 | E32: 目标：让他人能够复现项目并理解适用边界。 1）完善安装、导入、启动、评测命令和配置示例。 2）整理架构图、业务价值、指标和已知限制。 | F32: project-rag/README.md 与交付目录 | G32: 1）README 含从空环境到一次问答的完整步骤及脱敏配置示例。 2）固定评测可由一条命令启动，人工评分项有明确说明。 3）展示 1 个成功案例和 1 个失败案例，不虚报准确率或业务收益。 | H32: 未开始 | K32: 46327 | L32: 3.5 | M32: GitHub Docs：关于 README | N32: Python：虚拟环境 | P32: 原 Day34：项目一交付文档。
A33: P28 | B33: 4 | C33: 阶段一：补缺与 RAG 项目 | D33: 第四周项目一验收 | E33: 目标：确认项目一达到可演示、可测量的交付标准。 1）按周关口核对全量指标、引用、拒答、启动和已知风险。 2）做一次不看源码的 8 分钟讲解，只修复关口缺口。 | F33: reports/W04-review.md 与项目一验收结论 | G33: 1）按P19口径：20道有答案题命中至少16题，全部核心事实均有正确引用支持的回答至少17题；10道无答案题至少8题正确拒答。 2）独立集结果、失败例和运行证据可定位，未通过项不标完成。 3）未通过则插入补练并顺延P29及后续，不删除原任务。修复前另封存5题（3道有答案、2道无答案），修复冻结后首次测试；保留原独立成绩，已揭盲题仅作回归。 | H33: 未开始 | K33: 46328 | L33: 2.5 | M33: Microsoft Learn：RAG 概述 | N33: GitHub Docs：关于 README | P33: 原 Day35：项目一关口复盘，不新增理论。
A34: P29 | B34: 5 | C34: 阶段二：Agent 项目与工程交付 | D34: 单工具调用闭环 | E34: 目标：让模型通过受约束工具取得真实数据。 1）按 DeepSeek tool calling 接入一个无副作用的业务指标查询工具。 2）记录模型请求工具、执行结果和最终回答的完整链路。 | F34: 单工具 Demo 与 3 条调用轨迹 | G34: 1）3 个业务问题都展示工具名、合法参数和返回结果。 2）工具结果通过对应 tool_call_id 回传，最终回答使用实际结果。 3）至少 1 个无需工具的问题不强行触发工具。 | H34: 未开始 | K34: 46329 | L34: 3.5 | M34: DeepSeek：工具调用 | P34: 原 Day36：工具调用机制；业务数据取自已掌握 SQL 的结果。
A35: P30 | B35: 5 | C35: 阶段二：Agent 项目与工程交付 | D35: 工具参数与错误协议 | E35: 目标：让错误调用能够被识别并得到可理解的结果。 1）为工具定义严格参数结构与允许取值。 2）用未知工具、缺参数和错误日期等情况检验调用边界。 | F35: 工具 schema、错误格式和 5 个调用样例 | G35: 1）合法参数可执行，3 类非法参数在执行前被拒绝。 2）未知工具名不映射到任意函数或系统命令。 3）错误结果有稳定类别和说明，最终回答不会假称查询成功。 | H35: 未开始 | K35: 46330 | L35: 3.5 | M35: DeepSeek：工具调用 | N35: FastAPI：请求体 | P35: 原 Day37：工具接口和参数校验。
A36: P31 | B36: 5 | C36: 阶段二：Agent 项目与工程交付 | D36: 只读数据访问边界 | E36: 目标：让分析工具只能访问允许的数据且不能写入。 1）将脱敏演示数据放入独立 SQLite 副本，配置只读连接和表访问白名单。 2）增加最大返回行数和查询耗时限制，使用驱动权限控制阻止写操作。 | F36: 受限查询执行器与权限验证记录 | G36: 1）数据源以只读方式打开；测试前后文件内容哈希相同。 2）写入/删表/附加库/读取白名单外表至少 4 类请求被阻止。 3）查询最多100行，单值最多10KB、响应最多100KB，超时可中止；超限明确拒绝或标记截断。限制由驱动和执行器实施，不能只靠提示词或SELECT前缀。 | H36: 未开始 | K36: 46331 | L36: 3.75 | M36: Python：sqlite3 | N36: OWASP GenAI：过度自主权 | P36: 原 Day38：只读 NL2SQL 的执行安全集成；不重学 SQL。
A37: P32 | B37: 5 | C37: 阶段二：Agent 项目与工程交付 | D37: NL2SQL 工具集成 | E37: 目标：把自然语言问题连接到只读查询与可追溯结果。 1）向模型提供精简表结构、业务口径和受限查询工具。 2）选择 6 个已有业务问题，保存生成查询、执行结果及中文解释。 | F37: 自然语言查询接口与 6 条业务轨迹 | G37: 1）6 个问题至少 5 个得到与基准相同的关键数字。 2）每条回答可查看实际执行查询、数据时间范围和结果摘要。 3）执行失败不编造答案，允许最多 1 次修正后明确报错。 | H37: 未开始 | K37: 46332 | L37: 3.5 | M37: DeepSeek：工具调用 | N37: Python：sqlite3 | P37: 原 Day39：NL2SQL 业务集成；验证工具行为而非新增 SQL 考核。
A38: P33 | B38: 5 | C38: 阶段二：Agent 项目与工程交付 | D38: 两个工具的有界编排 | E38: 目标：让 Agent 在数据查询和知识检索间做受控选择。 1）复用项目一检索工具和项目二数据查询工具，不引入多 Agent 框架。 2）设置最多 3 次工具调用和总执行时限，并记录退出原因。 | F38: 两工具编排器与 6 条任务轨迹 | G38: 1）6 个问题覆盖仅检索、仅查数及组合任务，每类至少 2 个。 2）每条轨迹包含选择理由摘要、工具输入输出和耗时。 3）超过 3 次调用或总时限即退出并说明当前缺失信息，不无限循环。 | H38: 未开始 | K38: 46333 | L38: 3.5 | M38: DeepSeek：工具调用 | N38: OWASP GenAI：过度自主权 | P38: 原 Day40：轻量 Agent 编排与循环边界。
A39: P34 | B39: 5 | C39: 阶段二：Agent 项目与工程交付 | D39: 危险请求与失败退路 | E39: 目标：验证模型无法绕开只读和工具权限。 1）准备至少 6 个危险或异常请求：写入、删表、附库、越权表、提示注入和超大查询。 2）检查拒绝行为及工具故障时的用户提示。 | F39: 工具安全用例集与失败处理记录 | G39: 1）6 个危险请求全部被执行器阻止或安全限制，数据库哈希不变。 2）模拟工具超时与工具不可用时均有明确失败提示。 3）日志不包含密钥，错误响应不暴露数据库文件完整路径或堆栈。 | H39: 未开始 | K39: 46334 | L39: 3.5 | M39: OWASP GenAI：提示注入 | N39: Python：sqlite3 | P39: 原 Day41：只读工具安全与故障验证。
A40: P35 | B40: 5 | C40: 阶段二：Agent 项目与工程交付 | D40: 第五周工具链验收 | E40: 目标：确认工具链可靠后再构建业务分析页面。 1）复跑正常、错误和危险请求，检查权限与循环限制。 2）只修复最重要缺口，更新下一周风险。 | F40: reports/W05-review.md 与工具链验收表 | G40: 1）至少 6 个正常业务样例和 6 个危险样例均有完整记录。 2）能说明工具 schema、模型决策和执行器权限各自职责。 3）只读/限时/限行任一未通过时，插入S编号补练并顺延P36及后续，保留原任务，不扩大功能。 | H40: 未开始 | K40: 46335 | L40: 2.5 | M40: DeepSeek：工具调用 | N40: OWASP GenAI：过度自主权 | P40: 原 Day42：周复盘与缓冲，不新增理论。
A41: P36 | B41: 6 | C41: 阶段二：Agent 项目与工程交付 | D41: 分析业务口径 | E41: 目标：把 Agent 输出限定为可核对的业务分析。 1）确定一个分析使用者及 3 个决策问题，沿用脱敏演示数据。 2）写清 5 个核心指标的口径、时间范围、单位和空值规则。 | F41: project-analyst/docs/metrics.md 与用户故事 | G41: 1）3 个决策问题各有预期输出和对应数据来源。 2）5 个指标均有定义、单位、范围和基准示例。 3）明确数据是公开/模拟/脱敏，缺少因果证据时不得写因果结论。 | H41: 未开始 | K41: 46336 | L41: 3.5 | M41: Microsoft Learn：解决方案架构师职业路径 | N41: pandas：文件读写 | P41: 原 Day43：Business Analyst 业务需求与口径。
A42: P37 | B42: 6 | C42: 阶段二：Agent 项目与工程交付 | D42: 结构化分析报告 | E42: 目标：让数字、证据和建议形成可阅读的报告。 1）定义报告结构：问题、数据范围、发现、证据、限制和下一步。 2）把工具结果转换成报告，给每条数字结论附结果来源。 | F42: 报告生成模块与 3 份业务样例 | G42: 1）3 份报告的关键数字均能回溯到工具输出。 2）每份都有时间范围、样本量及至少 1 条限制。 3）建议与已知事实分开表达，不编造业务成效或原因。 | H42: 未开始 | K42: 46337 | L42: 3.5 | M42: DeepSeek：JSON Output | N42: DeepSeek：工具调用 | P42: 原 Day44：分析结论与报告生成。
A43: P38 | B43: 6 | C43: 阶段二：Agent 项目与工程交付 | D43: 图表与数据一致性 | E43: 目标：用已有可视化能力展示分析结果并避免数字错配。 1）复用现有图表经验，为 2 类问题生成柱状图或折线图。 2）使图表数据直接来自工具结果，补标题、单位和时间范围。 | F43: 2 类分析图表与数据对照记录 | G43: 1）至少 2 张图的所有展示数值与查询结果一致。 2）标题、坐标单位和时间范围完整，不用截断坐标夸大差异。 3）空数据与单点数据有明确提示，不生成误导性图表。 | H43: 未开始 | K43: 46338 | L43: 3.5 | M43: Streamlit：聊天应用教程 | N43: pandas：文件读写 | P43: 原 Day45：业务图表；复用已有图表技能。
A44: P39 | B44: 6 | C44: 阶段二：Agent 项目与工程交付 | D44: 分析应用页面 | E44: 目标：让使用者完成提问、查证、看图和导出。 1）用 Streamlit 整合问题输入、分析报告、图表和工具轨迹。 2）增加报告下载及会话重置，限制一次只运行一个分析任务。 | F44: Business Analyst 页面与操作说明 | G44: 1）3 个业务任务都能在页面完成并查看数据依据。 2）导出的报告含标题、时间范围和来源说明。 3）清空会话不残留上一位使用者的内容；两会话测试不相互污染。 | H44: 未开始 | K44: 46339 | L44: 3.5 | M44: Streamlit：聊天应用教程 | N44: Streamlit：Session State | P44: 原 Day46：分析应用交互与输出。
A45: P40 | B45: 6 | C45: 阶段二：Agent 项目与工程交付 | D45: 固定业务分析验收集 | E45: 目标：建立可回归的业务题集，同时保留未用于修复的验收问题。 1）整理12道开发/回归业务题及基准，覆盖汇总、对比、趋势与缺数据；另封存4道题（3道有数据、1道缺数据），P42前不运行。 2）固定版本运行并逐条核对数字、来源、限制和工具选择。 | F45: 12题开发/回归集、逐题评分与4题封存验收集 | G45: 1）12道开发题保存基准、实际结果和判定理由；4道封存题只保存问题与预期结果，未用于调参。 2）至少 10 题关键数字正确且来源可追溯；无数据题不编造。 3）危险请求集单独保留，不能用平均分掩盖权限失败。 | H45: 未开始 | K45: 46340 | L45: 3.5 | M45: pytest：入门 | N45: DeepSeek：工具调用 | P45: 原 Day47：分析 Agent 业务验收。
A46: P41 | B46: 6 | C46: 阶段二：Agent 项目与工程交付 | D46: 修复分析项目最大缺口 | E46: 目标：用失败证据确定修复，不扩展新功能。 1）按 P40 失败结果选择影响最大的 1–2 项问题。 2）修复后重跑受影响问题和危险请求，并录制短演示。 | F46: 修复对照表、回归记录与 3–5 分钟演示 | G46: 1）至少 1 项缺口有修复前后逐题结果；若无失败则检验一个边界案例。 2）12道开发/回归题至少10题业务结果与基准一致，6个危险请求均被阻止；4题封存集仍不运行。 3）演示中包含 1 个正常任务和 1 个安全拒绝/缺数据任务。 | H46: 未开始 | K46: 46341 | L46: 3.5 | M46: FastAPI：测试 | N46: OWASP GenAI：过度自主权 | P46: 原 Day48：项目二缺陷修复与演示。
... A49: P44 | B49: 7 | C49: 阶段二：Agent 项目与工程交付 | D49: 请求日志与诊断 | E49: 目标：让一次失败能被快速追踪到具体环节。 1）为 API、检索和工具调用统一请求 ID，记录状态与耗时。 2）模拟 3 类故障并通过日志定位，不记录密钥与完整敏感正文。 | F49: 日志配置、3 条故障定位记录 | G49: 1）一次请求能串起 API、检索/工具和模型调用的日志。 2）3 个故障都能在 5 分钟内定位到环节和错误类别。 3）抽查日志无密钥、敏感原文或完整个人数据；保留调试所需最小字段。 | H49: 未开始 | K49: 46344 | L49: 3.5 | M49: Python：日志教程 | N49: Microsoft Learn：卓越运营原则 | P49: 原 Day51：日志、故障诊断与运维基本功。
A50: P45 | B50: 7 | C50: 阶段二：Agent 项目与工程交付 | D50: 容器化已有 API | E50: 目标：将已工作的 API 变成可重复构建的交付单元。 1）为一个 API 制作 Dockerfile 和忽略规则，固定依赖版本。 2）构建镜像并启动容器，映射端口和数据卷。 | F50: Dockerfile、构建启动说明及容器 HTTP 记录 | G50: 1）镜像构建完成，容器内 /health 通过真实 HTTP 检查。 2）镜像不包含密钥或无关个人文件，配置从环境传入。 3）重建容器后持久化数据仍可使用；Docker 环境受阻则记录原因并优先修环境。 | H50: 未开始 | J50: 预计时长包含排错。安装/下载排错累计超过60分钟，就插入环境补课并顺延；保留现有环境，禁止把任务叠到同一天。 | K50: 46345 | L50: 3.75 | M50: Docker：入门实践 | N50: FastAPI：Docker 部署 | P50: 原 Day52：Docker；只容器化现有逻辑。
A51: P46 | B51: 7 | C51: 阶段二：Agent 项目与工程交付 | D51: 双项目部署与访问验证 | E51: 目标：让两个 Demo 按明确的访问方式运行。 1）将另一项目沿用同样方式打包，整理两个 Demo 的启动入口。 2）默认在本机完成容器部署；仅在已有授权和资源时使用远程主机。 | F51: 两项目部署说明与运行证据 | G51: 1）两项目均可启动，健康检查和各 1 条完整业务请求通过。 2）说明部署地址、端口、数据卷和配置位置，不把本地地址称为公网服务。 3）配置不开放无认证的公网工具接口；远程未做时明确写本机已验证。 | H51: 未开始 | K51: 46346 | L51: 3.5 | M51: FastAPI：Docker 部署 | N51: Python：虚拟环境 | P51: 原 Day53：部署与访问验收；不强制产生云费用。
A52: P47 | B52: 7 | C52: 阶段二：Agent 项目与工程交付 | D52: 持续集成 | E52: 目标：让每次代码改动自动检查关键离线行为。 1）为两个项目配置 GitHub Actions 的依赖安装和测试。 2）运行一次工作流，修复环境差异并保留结果链接。 | F52: CI 工作流及运行记录 | G52: 1）工作流在推送或手动触发后完成至少 1 次成功运行。 2）流程不需要真实模型密钥，不会运行收费模型调用。 3）若网络/权限阻碍托管运行，保留本地等价检查并标记远端未验收，不虚报 CI 成功。 | H52: 未开始 | K52: 46347 | L52: 3.5 | M52: GitHub Docs：构建和测试 Python | P52: 原 Day54：CI 与交付检查。
A53: P48 | B53: 7 | C53: 阶段二：Agent 项目与工程交付 | D53: 交接、重启与恢复 | E53: 目标：检验新环境运行和常见故障恢复。 1）在独立虚拟环境或干净容器中只按 README 复现两项目。 2）演练进程停止、缺配置或损坏测试索引中的 2 类情况，补恢复步骤。 | F53: 交接检查表与故障恢复手册 | G53: 1）两 Demo 都完成安装/启动、1 次 HTTP 检查和 1 个业务任务。 2）2 类故障均能按文档恢复，记录实际耗时。 3）依赖、示例数据、配置模板和评测入口齐全，无个人绝对路径依赖。 | H53: 未开始 | K53: 46348 | L53: 3.5 | M53: Python：虚拟环境 | N53: Microsoft Learn：可靠性原则 | P53: 原 Day55：可复现交接与恢复。
A54: P49 | B54: 7 | C54: 阶段二：Agent 项目与工程交付 | D54: 第七周工程交付验收 | E54: 目标：确认两个 Demo 能由文档驱动运行和维护。 1）核对独立环境复现、测试、部署、日志与恢复证据。 2）复盘剩余阻碍并决定是否进入方案周。 | F54: reports/W07-review.md 与工程交付清单 | G54: 1）两个 Demo 均有独立环境运行、真实 HTTP 和业务验收证据。 2）离线测试通过，托管 CI/公网部署状态如实记录。 3）关键运行缺口未清零则插入S编号补练，顺延P50及后续并保留原任务；本日不添加新框架。 | H54: 未开始 | K54: 46349 | L54: 2.5 | M54: GitHub Docs：关于 README | N54: Microsoft Learn：卓越运营原则 | P54: 原 Day56：周复盘与缓冲，不新增理论。
A55: P50 | B55: 8 | C55: 阶段三：解决方案与求职 | D55: 企业场景与需求访谈稿 | E55: 目标：基于已有 Demo 构造一个有边界的企业实施场景。 1）选一个中小企业部门的知识查询与经营分析场景，明确是假设案例。 2）写 10 个访谈问题，区分已知事实、假设和待确认事项。 | F55: 方案第 1–2 页：背景、目标与需求 | G55: 1）包含业务角色、当前流程、3 个痛点和 3 个可测目标。 2）至少 5 条关键假设有验证方式和负责人角色。 3）明确本轮范围、排除项和现有两 Demo 能覆盖的部分。 | H55: 未开始 | K55: 46350 | L55: 3.5 | M55: Microsoft Learn：解决方案架构师职业路径 | N55: Microsoft Learn：Well-Architected 框架 | P55: 原 Day57–58：合并需求发现与场景定义。
A56: P51 | B56: 8 | C56: 阶段三：解决方案与求职 | D56: 架构与数据流 | E56: 目标：用一张图讲清方案组件、边界和数据流向。 1）绘制用户、应用、模型、知识库和业务数据之间的数据流。 2）标注权限边界、外部依赖与失败后的处理路径。 | F56: 方案第 3–4 页：架构图与数据流 | G56: 1）图中每条主要连线都有输入/输出或接口说明。 2）明确原始数据、向量、日志的存储和访问边界。 3）至少 3 个失败点有降级/人工处理方式，能对应已有 Demo 证据。 | H56: 未开始 | K56: 46351 | L56: 3.5 | M56: Microsoft Learn：Well-Architected 框架 | N56: Microsoft Learn：RAG 概述 | P56: 原 Day59–60：合并系统架构与数据流。
A57: P52 | B57: 8 | C57: 阶段三：解决方案与求职 | D57: 技术选型与决策理由 | E57: 目标：说明为什么当前方案适合约束，而不是堆叠工具。 1）比较本地与托管部署、现有 DeepSeek 与一个候选模型/服务的适配。 2）按数据边界、效果、成本、维护四个维度写选型矩阵。 | F57: 方案第 5–6 页：选型矩阵与决策记录 | G57: 1）至少 2 个关键决策各比较 2 个备选方案。 2）每项结论有实测证据或明确标注的公开资料/假设。 3）列出更换选型的触发条件，不声称某工具普遍最优。 | H57: 未开始 | K57: 46352 | L57: 3.5 | M57: Microsoft Learn：Well-Architected 框架 | N57: DeepSeek：模型与价格 | P57: 原 Day61–62：合并模型、存储与部署选型。
A58: P53 | B58: 8 | C58: 阶段三：解决方案与求职 | D58: 实施、验收与职责 | E58: 目标：把方案拆成可执行的试点交付过程。 1）规划 4 个实施里程碑，写清产物、依赖和负责人角色。 2）把业务目标转换为 UAT 清单，并规划培训与交接。 | F58: 方案第 7–8 页：实施计划、职责与验收表 | G58: 1）4 个里程碑都有可检查产物、进入/退出条件和依赖。 2）至少 8 条 UAT 标准覆盖效果、来源、权限、运行和恢复。 3）客户/实施者/运维者职责清楚，包含试点失败退出或回滚条件。 | H58: 未开始 | K58: 46353 | L58: 3.5 | M58: Microsoft Learn：卓越运营原则 | N58: GitHub Docs：关于 README | P58: 原 Day63–64：合并实施、验收与交接设计。
A59: P54 | B59: 8 | C59: 阶段三：解决方案与求职 | D59: 风险、权限与运行方案 | E59: 目标：说明系统风险及可实施的控制措施。 1）列出数据、模型、权限、服务可用性和使用者误用风险。 2）为高优先级风险安排预防、监测、应对和责任角色。 | F59: 方案第 9–10 页：风险表、安全与运行说明 | G59: 1）至少 6 项风险有概率/影响、控制、责任角色和剩余风险。 2）明确数据保留、脱敏、最小权限、日志访问与只读工具边界。 3）至少 2 条风险控制已由现有 Demo 用例证明，其余标注待实施。 | H59: 未开始 | K59: 46354 | L59: 3.5 | M59: OWASP GenAI：提示注入 | N59: Microsoft Learn：可靠性原则 | P59: 原 Day65–66：合并风险、安全和运维设计。
A60: P55 | B60: 8 | C60: 阶段三：解决方案与求职 | D60: 成本、ROI 与完整方案 | E60: 目标：完成可核对假设的成本测算与实施方案初稿。 1）按低/中/高使用量估算模型、运行、维护和实施成本。 2）估算节省工时与盈亏平衡，整合为 10–15 页方案。 | F60: 10–15 页方案初稿与成本/ROI 计算表 | G60: 1）三档用量均给出调用量、token、单价日期、币种和维护假设。 2）ROI 含人工成本及采用率假设，并写清收益尚未真实验证。 3）方案覆盖需求、架构、选型、实施、验收、风险、成本和限制，页数 10–15。 | H60: 未开始 | K60: 46355 | L60: 3.75 | M60: Microsoft Learn：成本优化原则 | N60: DeepSeek：模型与价格 | P60: 原 Day67–69：合并成本、ROI 与方案整合。
A61: P56 | B61: 8 | C61: 阶段三：解决方案与求职 | D61: 第八周方案答辩与缓冲 | E61: 目标：确认第三项目可解释、可质疑、可落实。 1）进行 10 分钟方案讲解并回答 5 个质疑。 2）只修复事实不一致、缺少依据和验收不清的部分。 | F61: reports/W08-review.md、方案定稿与答辩记录 | G61: 1）10–15 页方案中的指标、成本和图示互相一致。 2）5 个问题覆盖数据安全、选型、失败处理、成本和上线验收。 3）无法回答的内容有明确待确认项；不把假设案例包装成真实客户案例。 | H61: 未开始 | K61: 46356 | L61: 2.5 | M61: Microsoft Learn：Well-Architected 框架 | N61: Microsoft Learn：解决方案架构师职业路径 | P61: 原 Day70：方案关口复盘，不新增理论。
A62: P57 | B62: 9 | C62: 阶段三：解决方案与求职 | D62: 整理两项目的对外说明 | E62: 目标：让招聘者快速判断项目做了什么以及做得如何。 1）为两个项目各写业务问题、本人工作、架构、运行和评测结果。 2）准备演示入口、截图、已知限制与真实失败案例。 | F62: 两个项目的作品集 README | G62: 1）每个 README 首页能找到场景、启动、演示和评测入口。 2）每个项目至少2项有来源的指标；区分开发/回归与首次独立测试的配置、题量和成绩，不将调参后的同题成绩称泛化能力。 3）贡献描述与代码和记录一致，不写虚构用户量或生产收益。 | H62: 未开始 | K62: 46357 | L62: 3.5 | M62: GitHub Docs：关于 README | P62: 原 Day71：项目作品集整理。
A63: P58 | B63: 9 | C63: 阶段三：解决方案与求职 | D63: 统一作品集入口 | E63: 目标：让两 Demo 和方案组成清晰可浏览的能力证据。 1）创建简单作品集索引，链接两个 Demo、方案和演示。 2）检查链接、公开文件和敏感信息，整理一页能力映射。 | F63: 作品集首页及公开前检查记录 | G63: 1）入口在 3 次点击内能找到两个 Demo、方案和运行说明。 2）全部本地/仓库链接逐项检查，无无效占位链接。 3）公开材料无密钥、私人数据和无授权文档；公开发布按实际授权操作。 | H63: 未开始 | K63: 46358 | L63: 3.5 | M63: GitHub Docs：管理个人主页 README | N63: GitHub Docs：从仓库中删除敏感数据 | P63: 原 Day72：统一展示和公开材料检查。
A64: P59 | B64: 9 | C64: 阶段三：解决方案与求职 | D64: 更新目标岗位匹配 | E64: 目标：用当前岗位样本决定简历重点和少量补缺。 1）更新至少 8 条近期目标岗位，含实施、解决方案与 AI 应用工程相关角色。 2）把高频要求映射到两 Demo 和方案证据，选出最值得投递的一组。 | F64: 岗位匹配矩阵 v2 与目标清单 | G64: 1）8 条岗位均有日期、链接、要求和匹配/差距说明。 2）至少 5 条高频能力能关联到具体项目证据。 3）只选不超过 3 项高价值差距；无法短期满足的年限要求如实标注。 | H64: 未开始 | K64: 46359 | L64: 3.5 | M64: Microsoft Learn：解决方案架构师职业路径 | N64: National Careers Service：撰写简历 | P64: 原 Day73：岗位分析与投递定位。
A65: P60 | B65: 9 | C65: 阶段三：解决方案与求职 | D65: 按岗位写两版简历 | E65: 目标：用可验证成果表达 AI 实施和应用能力。 1）制作偏实施/解决方案和偏 AI 应用工程两版简历。 2）为每个项目写 3–4 条问题、行动、结果描述，并核对事实。 | F65: 两版简历与事实核对表 | G65: 1）两版各 1–2 页，前半页能看出目标岗位和相关能力。 2）每条量化成果都能在评测或运行记录中找到依据。 3）保留真实教育/经历，未知信息留待本人补充，不编造工作年限或客户。 | H65: 未开始 | K65: 46360 | L65: 3.5 | M65: National Careers Service：撰写简历 | N65: GitHub Docs：关于 README | P65: 原 Day74：岗位化简历。
A66: P61 | B66: 9 | C66: 阶段三：解决方案与求职 | D66: 技术项目模拟面试 | E66: 目标：检验是否能独立解释实现、取舍和失败。 1）录制或进行一次 30–40 分钟模拟面试，覆盖 RAG 和工具调用。 2）逐题标记正确、含糊和不会，复查相关代码与证据。 | F66: 模拟面试 1 记录与改进清单 | G66: 1）至少回答 10 个问题，覆盖分块、评测、引用、只读、超时和部署。 2）能从一条失败案例解释定位过程及取舍，不只背定义。 3）选出最多 3 个薄弱点，各写一个当天可执行的补法。 | H66: 未开始 | K66: 46361 | L66: 3.5 | M66: National Careers Service：面试建议 | N66: Microsoft Learn：RAG 概述 | P66: 原 Day75：技术面试与项目解释。
A67: P62 | B67: 9 | C67: 阶段三：解决方案与求职 | D67: 方案与客户沟通模拟 | E67: 目标：检验需求澄清和方案解释能力。 1）进行第二次模拟：5 分钟需求澄清、10 分钟方案说明、10 分钟质疑。 2）用 STAR 整理 3 个真实学习/项目故事，修订表达。 | F67: 模拟面试 2 记录与 3 个项目故事 | G67: 1）先确认业务目标和约束，再说明方案，不直接堆工具名称。 2）能回答成本过高、数据不能外发、效果不达标三类问题。 3）3 个故事均包含本人行动、实际结果和反思，不伪装为真实客户交付。 | H67: 未开始 | K67: 46362 | L67: 3.5 | M67: National Careers Service：STAR 面试方法 | N67: Microsoft Learn：解决方案架构师职业路径 | P67: 原 Day76：方案沟通与行为面试。
A68: P63 | B68: 9 | C68: 阶段三：解决方案与求职 | D68: 第九周求职材料验收 | E68: 目标：确认材料与演示已经可以用于真实投递。 1）核对作品集、两版简历、岗位匹配与两次模拟面试。 2）只修复投递前最重要的 1–2 个缺口。 | F68: reports/W09-review.md 与投递准备清单 | G68: 1）两 Demo、方案、演示和简历链接均有效且可访问。 2）抽查 5 条简历成果都能定位到证据。 3）剩余薄弱点最多列 3 项并排优先级；严重事实或隐私问题未解决则先修复。 | H68: 未开始 | K68: 46363 | L68: 2.5 | M68: National Careers Service：撰写简历 | N68: National Careers Service：面试建议 | P68: 原 Day77：周复盘与缓冲，不新增理论。
A69: P64 | B69: 10 | C69: 阶段三：解决方案与求职 | D69: 第一批匹配投递 | E69: 目标：把材料用于真实岗位并建立可回访记录。 1）从目标清单选择 3 个匹配岗位，逐条调整简历重点。 2）由本人确认材料并完成投递，记录版本、渠道和日期。 | F69: 3 条投递记录与对应简历版本 | G69: 1）至少 3 个岗位有匹配理由及差距说明。 2）本人完成 3 次投递并记录凭据；岗位失效等阻碍如实记录并换候选。 3）不自动代发私人消息，不承诺投递必然带来面试或 offer。 | H69: 未开始 | K69: 46364 | L69: 3.5 | M69: National Careers Service：撰写简历 | N69: National Careers Service：面试建议 | P69: 原 Day78：真实投递第一批。
A70: P65 | B70: 10 | C70: 阶段三：解决方案与求职 | D70: 定向修复一个求职缺口 | E70: 目标：用岗位要求或模拟反馈提升最薄弱的证据。 1）从真实反馈/岗位矩阵选择一个高频且可当天解决的问题。 2）做最小修复或补证据，再更新对应简历和作品集。 | F70: 一项定向补缺产物与前后对照 | G70: 1）说明缺口来自哪条反馈或至少 3 条岗位要求。 2）补缺限定为 1 项，包含可运行/可演示/可核对结果。 3）缺少真实招聘反馈时明确使用模拟或岗位反馈，不编造回复。 | H70: 未开始 | K70: 46365 | L70: 3.5 | M70: GitHub Docs：关于 README | N70: National Careers Service：面试建议 | P70: 原 Day79：反馈驱动补缺。
A71: P66 | B71: 10 | C71: 阶段三：解决方案与求职 | D71: 第二批匹配投递 | E71: 目标：验证修订后的材料并扩大合适机会。 1）选择另外 3 个匹配岗位，检查要求与项目证据对应关系。 2）本人完成第二批投递，比较两批材料与岗位差异。 | F71: 累计至少 6 条投递记录与版本对照 | G71: 1）新增 3 次由本人完成的投递，或记录具体客观阻碍与替代岗位。 2）每条记录含岗位链接、时间、简历版本、当前状态和下次查看日期。 3）不把没有回复视为技术能力结论，不据此盲目重做项目。 | H71: 未开始 | K71: 46366 | L71: 3.5 | M71: National Careers Service：撰写简历 | N71: National Careers Service：STAR 面试方法 | P71: 原 Day80：真实投递第二批。
A72: P67 | B72: 10 | C72: 阶段三：解决方案与求职 | D72: 陌生问题现场演示 | E72: 目标：检验能否应对未排练的业务问题和常见追问。 1）给两个 Demo 各准备 3 道未用于调参的新题，现场运行。 2）完成一次 15 分钟演示，主动说明限制与失败处理。 | F72: 6 道新题结果与现场演示记录 | G72: 1）6 道题全部记录结果及判定依据，不只选成功题。 2）两项目各至少 2 道正常业务题达到预期；不足则记录待修复项。 3）能够解释任何失败发生在数据、检索、模型、工具还是界面环节。 | H72: 未开始 | K72: 46367 | L72: 3.5 | M72: Microsoft Learn：RAG 概述 | N72: National Careers Service：面试建议 | P72: 原 Day81：陌生场景与面试演示。
A73: P68 | B73: 10 | C73: 阶段三：解决方案与求职 | D73: 双 Demo 独立复现终验 | E73: 目标：确认最终作品可以脱离当前开发会话运行。 1）在独立环境从 README 启动两项目，执行固定评测和业务请求。 2）核对依赖、数据、配置示例和恢复步骤，修复阻断问题。 | F73: 两个 Demo 最终复现记录与评测快照 | G73: 1）两项目均完成独立环境安装、启动、真实 HTTP 和一条完整业务流程。 2）RAG固定集、分析12题回归集按原口径报告；独立集注明首次测试或已揭盲后回归；安全用例全部通过。 3）未验证的远程部署或真实模型路径明确标出，不能以离线替身代替。 | H73: 未开始 | K73: 46368 | L73: 3.75 | M73: Python：虚拟环境 | N73: GitHub Docs：关于 README | P73: 原 Day82：作品工程终验。
A74: P69 | B74: 10 | C74: 阶段三：解决方案与求职 | D74: 方案与个人能力终验 | E74: 目标：检验能否把业务目标、系统行为和交付计划连起来讲清。 1）按 10–15 页方案做 10 分钟讲解，回答 5 个新追问。 2）核对简历、作品集、方案和评测的事实一致性。 | F74: 终验答辩记录与能力证据矩阵 | G74: 1）两 Demo 和方案都能说明业务问题、实现、指标、限制及下一步。 2）5 个追问至少 4 个有具体回答；不会的如实记录待确认与查证方式。 3）抽查 8 条成果描述无互相矛盾、虚构客户或未经验证的收益。 | H74: 未开始 | K74: 46369 | L74: 3.5 | M74: Microsoft Learn：Well-Architected 框架 | N74: National Careers Service：STAR 面试方法 | P74: 原 Day83：方案与能力终验。
A75: P70 | B75: 10 | C75: 阶段三：解决方案与求职 | D75: 第十周总复盘与下一轮计划 | E75: 目标：据证据决定后续两周优先事项，并持续跟踪投递。 1）汇总完成、未完成、耗时和投递反馈，区分能力缺口与外部阻碍。 2）只安排下一轮最重要的 3 项行动，延续每日跟进。 | F75: reports/W10-review.md、最终验收表与下一轮两周清单 | G75: 1）两可复现 Demo、一份 10–15 页方案、固定评测和独立解释逐项给出证据/缺口。 2）累计至少 6 次匹配投递或明确记录阻碍；未获 offer 不等于本计划未完成。 3）下一轮 3 项行动各有目标、预计时长和验收；未完成项保留原 ID 与历史记录。 | H75: 未开始 | K75: 46370 | L75: 2.5 | M75: GitHub Docs：关于 README | N75: National Careers Service：面试建议 | P75: 原 Day84：最终复盘与持续调整，不新增理论。

Sheet 学习资料
A2: 学习资料与阅读范围
A3: 按每日清单中的链接学习；先读推荐部分，再用当天产出检验理解。
A5: 编号 | B5: 资料名称 | C5: 链接 | D5: 推荐阅读部分
A6: fastapi-first | B6: FastAPI：第一步与接口文档 | C6: https://fastapi.tiangolo.com/zh/tutorial/first-steps/ | D6: 启动已有服务、读取 /docs、实际发送 HTTP 请求；无需重新通读基础教程。
A7: fastapi-body | B7: FastAPI：请求体 | C7: https://fastapi.tiangolo.com/zh/tutorial/body/ | D7: 请求模型、字段校验及 422 错误；用于数据分析与聊天接口。
A8: fastapi-errors | B8: FastAPI：处理错误 | C8: https://fastapi.tiangolo.com/zh/tutorial/handling-errors/ | D8: 用 HTTPException 返回业务错误，区分输入错误与服务故障。
A9: fastapi-test | B9: FastAPI：测试 | C9: https://fastapi.tiangolo.com/zh/tutorial/testing/ | D9: TestClient、正常及错误路径；后续仍要补真实 HTTP 检查。
A10: fastapi-cors | B10: FastAPI：跨域 | C10: https://fastapi.tiangolo.com/zh/tutorial/cors/ | D10: 仅在前后端分离需要时配置允许来源，避免任意开放。
A11: pandas-missing | B11: pandas：缺失数据 | C11: https://pandas.pydata.org/docs/user_guide/missing_data.html | D11: 只读缺失值识别与处理部分，补可复现清洗，不重学 Pandas。
A12: pandas-io | B12: pandas：文件读写 | C12: https://pandas.pydata.org/docs/user_guide/io.html | D12: read_csv、to_csv、dtype 与输出路径；保留原数据。
A13: python-venv | B13: Python：虚拟环境 | C13: https://docs.python.org/zh-cn/3/library/venv.html | D13: 为两个 Demo 建独立环境并记录安装、启动命令。
A14: python-logging | B14: Python：日志教程 | C14: https://docs.python.org/zh-cn/3/howto/logging.html | D14: 日志级别、结构化字段与错误上下文；避免记录密钥及敏感正文。
A15: python-sqlite | B15: Python：sqlite3 | C15: https://docs.python.org/zh-cn/3/library/sqlite3.html | D15: 只读 URI、set_authorizer、set_progress_handler；只用于工具集成与安全限制。
A16: deepseek-first | B16: DeepSeek：首次调用 | C16: https://api-docs.deepseek.com/zh-cn/ | D16: 沿用现有兼容 SDK 和模型配置，核对基础调用参数。
... A46: interview | B46: National Careers Service：面试建议 | C46: https://nationalcareers.service.gov.uk/careers-advice/interview-advice | D46: 准备岗位、项目解释、问题与面后复盘。
